qfetch/__init__.py
quickfetch-0.1.0.dist-info/licenses/LICENSE
quickfetch-0.1.0.dist-info/METADATA
quickfetch-0.1.0.dist-info/WHEEL
quickfetch-0.1.0.dist-info/entry_points.txt
quickfetch-0.1.0.dist-info/top_level.txt
quickfetch-0.1.0.dist-info/RECORD
