Metadata-Version: 2.4
Name: quickfetch
Version: 0.1.0
Summary: Fast, simple, and beautifully minimal web scraping
Home-page: https://github.com/quickfetch/quickfetch
Author: quickfetch
Author-email: quickfetch <quickfetch@example.com>
Maintainer-email: quickfetch <quickfetch@example.com>
License: MIT
Project-URL: Homepage, https://github.com/quickfetch/quickfetch
Project-URL: Documentation, https://github.com/quickfetch/quickfetch#readme
Project-URL: Repository, https://github.com/quickfetch/quickfetch
Project-URL: Bug Tracker, https://github.com/quickfetch/quickfetch/issues
Keywords: web scraping,http,html,json,requests,beautifulsoup,lxml
Classifier: Development Status :: 4 - Beta
Classifier: Intended Audience :: Developers
Classifier: License :: OSI Approved :: MIT License
Classifier: Operating System :: OS Independent
Classifier: Programming Language :: Python :: 3
Classifier: Programming Language :: Python :: 3.8
Classifier: Programming Language :: Python :: 3.9
Classifier: Programming Language :: Python :: 3.10
Classifier: Programming Language :: Python :: 3.11
Classifier: Programming Language :: Python :: 3.12
Classifier: Topic :: Internet :: WWW/HTTP
Classifier: Topic :: Software Development :: Libraries :: Python Modules
Classifier: Topic :: Text Processing :: Markup :: HTML
Requires-Python: >=3.8
License-File: LICENSE
Requires-Dist: requests>=2.25.0
Requires-Dist: selectolax>=0.3.0
Provides-Extra: dev
Requires-Dist: pytest>=6.0; extra == "dev"
Requires-Dist: pytest-cov>=2.0; extra == "dev"
Requires-Dist: black>=21.0; extra == "dev"
Requires-Dist: flake8>=3.8; extra == "dev"
Requires-Dist: mypy>=0.800; extra == "dev"
Dynamic: author
Dynamic: home-page
Dynamic: license-file
Dynamic: requires-python
